[
  {
    "id": 1,
    "name": "Cora Vasut",
    "position": "President",
    "image": "/teamimages/CoraVasut.png",
    "link": "https://www.linkedin.com/in/coravasut/",
    "linkedIn": true
  },
  {
    "id": 2,
    "name": "Blal Idrees",
    "position": "VPI",
    "image": "/teamimages/BlalIdrees.png",
    "link": "https://www.linkedin.com/in/blal-idrees-aa07201a5/",
    "linkedIn": true

  },
  {
    "id": 3,
    "name": "Vacancy",
    "position": "VPE",
    "image": "/teamimages/genericProfile.png"

  },
  {
    "id": 4,
    "name": "Samira Mehdi",
    "position": "VPO",
    "image": "/teamimages/SamiraMehdi.png",
    "link": "https://www.linkedin.com/in/samira-mehdi-32ba661a3",
    "linkedIn": true

  }
]
